abf_openai/__init__.py
abf_openai/cached_client.py
abf_openai/main.py
abf_openai/materialize_utils.py
abf_openai/utils.py
abf_openai-0.0.14.dist-info/METADATA
abf_openai-0.0.14.dist-info/WHEEL
abf_openai-0.0.14.dist-info/licenses/LICENSE
abf_openai-0.0.14.dist-info/RECORD
