Metadata-Version: 2.4
Name: abf_openai
Version: 0.0.14
Summary: A version of the OpenAI package that allows the caching of responses, tailored for the CBSxWallStreetPrep 'AI in Business and Finance' class.
Project-URL: Homepage, https://github.com/danguetta/cached_openai
Project-URL: Issues, https://github.com/danguetta/cached_openai/issues
Author-email: Daniel Guetta <daniel@guetta.com>
License-Expression: MIT
License-File: LICENSE
Classifier: Operating System :: OS Independent
Classifier: Programming Language :: Python :: 3
Requires-Python: >=3.8
Requires-Dist: numpy>=1.26.1
Requires-Dist: openai>=1.66.2
Requires-Dist: requests>=2.32.2
Requires-Dist: tqdm>=4.67.1
